tbnu/Database.py
tbnu/Handler.py
tbnu/Note.py
tbnu/__init__.py
tbnu/__main__.py
tbnu/aesthetics/__init__.py
tbnu/aesthetics/colors.py
tbnu/aesthetics/logos.py
tbnu-1.0.1.dist-info/entry_points.txt
tbnu-1.0.1.dist-info/WHEEL
tbnu-1.0.1.dist-info/METADATA
tbnu-1.0.1.dist-info/RECORD
